{
  "generatedAt": "2026-05-25T05:48:52.738055Z",
  "timezone": "Asia/Tokyo",
  "today": "2026-05-25",
  "month": "2026-05",
  "note": "Hermes uses local sessions table usage. Symphony uses Codex rollout token_count events from Symphony-launched workers. This is not provider billing.",
  "categories": {
    "hermes": {
      "label": "Hermes Agent",
      "today": {
        "tokens": 100645969,
        "input": 5821112,
        "output": 284050,
        "cache": 94475776,
        "reasoning": 65031,
        "sessions": 40
      },
      "month": {
        "tokens": 1099269000,
        "input": 86480797,
        "output": 4667911,
        "cache": 1007259136,
        "reasoning": 861156,
        "sessions": 862
      },
      "allTime": {
        "tokens": 1099269000,
        "input": 86480797,
        "output": 4667911,
        "cache": 1007259136,
        "reasoning": 861156,
        "sessions": 862
      }
    },
    "symphony": {
      "label": "Symphony",
      "today": {
        "tokens": 279651966,
        "input": 279011579,
        "output": 640387,
        "cache": 273977856,
        "reasoning": 302922,
        "sessions": 23
      },
      "month": {
        "tokens": 10115980963,
        "input": 10097843098,
        "output": 18137865,
        "cache": 9866327808,
        "reasoning": 7177023,
        "sessions": 237
      },
      "allTime": {
        "tokens": 10115980963,
        "input": 10097843098,
        "output": 18137865,
        "cache": 9866327808,
        "reasoning": 7177023,
        "sessions": 237
      }
    },
    "total": {
      "label": "Total",
      "today": {
        "tokens": 380297935,
        "input": 284832691,
        "output": 924437,
        "cache": 368453632,
        "reasoning": 367953,
        "sessions": 63
      },
      "month": {
        "tokens": 11215249963,
        "input": 10184323895,
        "output": 22805776,
        "cache": 10873586944,
        "reasoning": 8038179,
        "sessions": 1099
      },
      "allTime": {
        "tokens": 11215249963,
        "input": 10184323895,
        "output": 22805776,
        "cache": 10873586944,
        "reasoning": 8038179,
        "sessions": 1099
      }
    }
  }
}
