{
  "generatedAt": "2026-05-27T09:16:09.206920Z",
  "timezone": "Asia/Tokyo",
  "today": "2026-05-27",
  "month": "2026-05",
  "note": "Hermes uses local sessions table usage. Symphony uses Codex rollout token_count events from Symphony-launched workers. This is not provider billing.",
  "categories": {
    "hermes": {
      "label": "Hermes Agent",
      "today": {
        "tokens": 1793471,
        "input": 1775501,
        "output": 17970,
        "cache": 0,
        "reasoning": 0,
        "sessions": 5
      },
      "month": {
        "tokens": 1227419712,
        "input": 98423754,
        "output": 5264518,
        "cache": 1122765824,
        "reasoning": 965616,
        "sessions": 965
      },
      "allTime": {
        "tokens": 1227419712,
        "input": 98423754,
        "output": 5264518,
        "cache": 1122765824,
        "reasoning": 965616,
        "sessions": 965
      }
    },
    "symphony": {
      "label": "Symphony",
      "today": {
        "tokens": 32822512,
        "input": 32680459,
        "output": 142053,
        "cache": 31787648,
        "reasoning": 48896,
        "sessions": 5
      },
      "month": {
        "tokens": 11385217614,
        "input": 11365014618,
        "output": 20202996,
        "cache": 11103164416,
        "reasoning": 8086664,
        "sessions": 255
      },
      "allTime": {
        "tokens": 11385217614,
        "input": 11365014618,
        "output": 20202996,
        "cache": 11103164416,
        "reasoning": 8086664,
        "sessions": 255
      }
    },
    "total": {
      "label": "Total",
      "today": {
        "tokens": 34615983,
        "input": 34455960,
        "output": 160023,
        "cache": 31787648,
        "reasoning": 48896,
        "sessions": 10
      },
      "month": {
        "tokens": 12612637326,
        "input": 11463438372,
        "output": 25467514,
        "cache": 12225930240,
        "reasoning": 9052280,
        "sessions": 1220
      },
      "allTime": {
        "tokens": 12612637326,
        "input": 11463438372,
        "output": 25467514,
        "cache": 12225930240,
        "reasoning": 9052280,
        "sessions": 1220
      }
    }
  }
}
