{
  "generatedAt": "2026-05-21T20:54:19.998814Z",
  "timezone": "Asia/Tokyo",
  "today": "2026-05-22",
  "month": "2026-05",
  "note": "Hermes uses local sessions table usage. Symphony uses Codex rollout token_count events from Symphony-launched workers. This is not provider billing.",
  "categories": {
    "hermes": {
      "label": "Hermes Agent",
      "today": {
        "tokens": 2051854,
        "input": 115175,
        "output": 6408,
        "cache": 1928704,
        "reasoning": 1567,
        "sessions": 2
      },
      "month": {
        "tokens": 923321605,
        "input": 74893918,
        "output": 4148676,
        "cache": 843531776,
        "reasoning": 747235,
        "sessions": 751
      },
      "allTime": {
        "tokens": 923321605,
        "input": 74893918,
        "output": 4148676,
        "cache": 843531776,
        "reasoning": 747235,
        "sessions": 751
      }
    },
    "symphony": {
      "label": "Symphony",
      "today": {
        "tokens": 0,
        "input": 0,
        "output": 0,
        "cache": 0,
        "reasoning": 0,
        "sessions": 0
      },
      "month": {
        "tokens": 7289348883,
        "input": 7275297541,
        "output": 14051342,
        "cache": 7103996928,
        "reasoning": 5367865,
        "sessions": 213
      },
      "allTime": {
        "tokens": 7289348883,
        "input": 7275297541,
        "output": 14051342,
        "cache": 7103996928,
        "reasoning": 5367865,
        "sessions": 213
      }
    },
    "total": {
      "label": "Total",
      "today": {
        "tokens": 2051854,
        "input": 115175,
        "output": 6408,
        "cache": 1928704,
        "reasoning": 1567,
        "sessions": 2
      },
      "month": {
        "tokens": 8212670488,
        "input": 7350191459,
        "output": 18200018,
        "cache": 7947528704,
        "reasoning": 6115100,
        "sessions": 964
      },
      "allTime": {
        "tokens": 8212670488,
        "input": 7350191459,
        "output": 18200018,
        "cache": 7947528704,
        "reasoning": 6115100,
        "sessions": 964
      }
    }
  }
}
