{
  "generatedAt": "2026-05-21T05:25:27.783003Z",
  "timezone": "Asia/Tokyo",
  "today": "2026-05-21",
  "month": "2026-05",
  "note": "Hermes uses local sessions table usage. Symphony uses Codex rollout token_count events from Symphony-launched workers. This is not provider billing.",
  "categories": {
    "hermes": {
      "label": "Hermes Agent",
      "today": {
        "tokens": 132045444,
        "input": 8268304,
        "output": 482973,
        "cache": 123204096,
        "reasoning": 90071,
        "sessions": 64
      },
      "month": {
        "tokens": 803231355,
        "input": 68470680,
        "output": 3786400,
        "cache": 730299392,
        "reasoning": 674883,
        "sessions": 703
      },
      "allTime": {
        "tokens": 803231355,
        "input": 68470680,
        "output": 3786400,
        "cache": 730299392,
        "reasoning": 674883,
        "sessions": 703
      }
    },
    "symphony": {
      "label": "Symphony",
      "today": {
        "tokens": 2142018054,
        "input": 2137150389,
        "output": 4867665,
        "cache": 2085579904,
        "reasoning": 1833048,
        "sessions": 81
      },
      "month": {
        "tokens": 5439133444,
        "input": 5427665486,
        "output": 11467958,
        "cache": 5289624448,
        "reasoning": 4302436,
        "sessions": 171
      },
      "allTime": {
        "tokens": 5439133444,
        "input": 5427665486,
        "output": 11467958,
        "cache": 5289624448,
        "reasoning": 4302436,
        "sessions": 171
      }
    },
    "total": {
      "label": "Total",
      "today": {
        "tokens": 2274063498,
        "input": 2145418693,
        "output": 5350638,
        "cache": 2208784000,
        "reasoning": 1923119,
        "sessions": 145
      },
      "month": {
        "tokens": 6242364799,
        "input": 5496136166,
        "output": 15254358,
        "cache": 6019923840,
        "reasoning": 4977319,
        "sessions": 874
      },
      "allTime": {
        "tokens": 6242364799,
        "input": 5496136166,
        "output": 15254358,
        "cache": 6019923840,
        "reasoning": 4977319,
        "sessions": 874
      }
    }
  }
}
