{
  "generatedAt": "2026-05-31T19:08:06.715801Z",
  "timezone": "Asia/Tokyo",
  "today": "2026-06-01",
  "month": "2026-06",
  "note": "Hermes uses local sessions table usage. Symphony uses Codex rollout token_count events from Symphony-launched workers. This is not provider billing.",
  "categories": {
    "hermes": {
      "label": "Hermes Agent",
      "today": {
        "tokens": 0,
        "input": 0,
        "output": 0,
        "cache": 0,
        "reasoning": 0,
        "sessions": 0
      },
      "month": {
        "tokens": 0,
        "input": 0,
        "output": 0,
        "cache": 0,
        "reasoning": 0,
        "sessions": 0
      },
      "allTime": {
        "tokens": 2036821791,
        "input": 133768863,
        "output": 8156702,
        "cache": 1892650496,
        "reasoning": 2245730,
        "sessions": 1174
      }
    },
    "symphony": {
      "label": "Symphony",
      "today": {
        "tokens": 217864242,
        "input": 217410380,
        "output": 453862,
        "cache": 214063104,
        "reasoning": 146006,
        "sessions": 11
      },
      "month": {
        "tokens": 217864242,
        "input": 217410380,
        "output": 453862,
        "cache": 214063104,
        "reasoning": 146006,
        "sessions": 11
      },
      "allTime": {
        "tokens": 16696984517,
        "input": 16663714550,
        "output": 33269967,
        "cache": 16296334080,
        "reasoning": 12427532,
        "sessions": 507
      }
    },
    "total": {
      "label": "Total",
      "today": {
        "tokens": 217864242,
        "input": 217410380,
        "output": 453862,
        "cache": 214063104,
        "reasoning": 146006,
        "sessions": 11
      },
      "month": {
        "tokens": 217864242,
        "input": 217410380,
        "output": 453862,
        "cache": 214063104,
        "reasoning": 146006,
        "sessions": 11
      },
      "allTime": {
        "tokens": 18733806308,
        "input": 16797483413,
        "output": 41426669,
        "cache": 18188984576,
        "reasoning": 14673262,
        "sessions": 1681
      }
    }
  }
}
