{
  "generatedAt": "2026-05-22T02:57:30.047658Z",
  "timezone": "Asia/Tokyo",
  "today": "2026-05-22",
  "month": "2026-05",
  "note": "Hermes uses local sessions table usage. Symphony uses Codex rollout token_count events from Symphony-launched workers. This is not provider billing.",
  "categories": {
    "hermes": {
      "label": "Hermes Agent",
      "today": {
        "tokens": 17233009,
        "input": 1380189,
        "output": 52123,
        "cache": 15791104,
        "reasoning": 9593,
        "sessions": 16
      },
      "month": {
        "tokens": 938502760,
        "input": 76158932,
        "output": 4194391,
        "cache": 857394176,
        "reasoning": 755261,
        "sessions": 765
      },
      "allTime": {
        "tokens": 938502760,
        "input": 76158932,
        "output": 4194391,
        "cache": 857394176,
        "reasoning": 755261,
        "sessions": 765
      }
    },
    "symphony": {
      "label": "Symphony",
      "today": {
        "tokens": 68296621,
        "input": 68193219,
        "output": 103402,
        "cache": 67105536,
        "reasoning": 38218,
        "sessions": 1
      },
      "month": {
        "tokens": 7920653253,
        "input": 7905796102,
        "output": 14857151,
        "cache": 7720361984,
        "reasoning": 5697700,
        "sessions": 214
      },
      "allTime": {
        "tokens": 7920653253,
        "input": 7905796102,
        "output": 14857151,
        "cache": 7720361984,
        "reasoning": 5697700,
        "sessions": 214
      }
    },
    "total": {
      "label": "Total",
      "today": {
        "tokens": 85529630,
        "input": 69573408,
        "output": 155525,
        "cache": 82896640,
        "reasoning": 47811,
        "sessions": 17
      },
      "month": {
        "tokens": 8859156013,
        "input": 7981955034,
        "output": 19051542,
        "cache": 8577756160,
        "reasoning": 6452961,
        "sessions": 979
      },
      "allTime": {
        "tokens": 8859156013,
        "input": 7981955034,
        "output": 19051542,
        "cache": 8577756160,
        "reasoning": 6452961,
        "sessions": 979
      }
    }
  }
}
