{
  "generatedAt": "2026-05-26T07:22:02.700177Z",
  "timezone": "Asia/Tokyo",
  "today": "2026-05-26",
  "month": "2026-05",
  "note": "Hermes uses local sessions table usage. Symphony uses Codex rollout token_count events from Symphony-launched workers. This is not provider billing.",
  "categories": {
    "hermes": {
      "label": "Hermes Agent",
      "today": {
        "tokens": 50287556,
        "input": 4108151,
        "output": 262774,
        "cache": 45867008,
        "reasoning": 49623,
        "sessions": 42
      },
      "month": {
        "tokens": 1160067479,
        "input": 91669269,
        "output": 4997203,
        "cache": 1062478848,
        "reasoning": 922159,
        "sessions": 916
      },
      "allTime": {
        "tokens": 1160067479,
        "input": 91669269,
        "output": 4997203,
        "cache": 1062478848,
        "reasoning": 922159,
        "sessions": 916
      }
    },
    "symphony": {
      "label": "Symphony",
      "today": {
        "tokens": 0,
        "input": 0,
        "output": 0,
        "cache": 0,
        "reasoning": 0,
        "sessions": 0
      },
      "month": {
        "tokens": 10964462542,
        "input": 10944926458,
        "output": 19536084,
        "cache": 10693644288,
        "reasoning": 7828375,
        "sessions": 247
      },
      "allTime": {
        "tokens": 10964462542,
        "input": 10944926458,
        "output": 19536084,
        "cache": 10693644288,
        "reasoning": 7828375,
        "sessions": 247
      }
    },
    "total": {
      "label": "Total",
      "today": {
        "tokens": 50287556,
        "input": 4108151,
        "output": 262774,
        "cache": 45867008,
        "reasoning": 49623,
        "sessions": 42
      },
      "month": {
        "tokens": 12124530021,
        "input": 11036595727,
        "output": 24533287,
        "cache": 11756123136,
        "reasoning": 8750534,
        "sessions": 1163
      },
      "allTime": {
        "tokens": 12124530021,
        "input": 11036595727,
        "output": 24533287,
        "cache": 11756123136,
        "reasoning": 8750534,
        "sessions": 1163
      }
    }
  }
}
