{
  "generatedAt": "2026-05-22T09:47:07.828331Z",
  "timezone": "Asia/Tokyo",
  "today": "2026-05-22",
  "month": "2026-05",
  "note": "Hermes uses local sessions table usage. Symphony uses Codex rollout token_count events from Symphony-launched workers. This is not provider billing.",
  "categories": {
    "hermes": {
      "label": "Hermes Agent",
      "today": {
        "tokens": 58521575,
        "input": 3114226,
        "output": 156767,
        "cache": 55216640,
        "reasoning": 33942,
        "sessions": 27
      },
      "month": {
        "tokens": 979791326,
        "input": 77892969,
        "output": 4299035,
        "cache": 896819712,
        "reasoning": 779610,
        "sessions": 776
      },
      "allTime": {
        "tokens": 979791326,
        "input": 77892969,
        "output": 4299035,
        "cache": 896819712,
        "reasoning": 779610,
        "sessions": 776
      }
    },
    "symphony": {
      "label": "Symphony",
      "today": {
        "tokens": 68296621,
        "input": 68193219,
        "output": 103402,
        "cache": 67105536,
        "reasoning": 38218,
        "sessions": 1
      },
      "month": {
        "tokens": 8265741282,
        "input": 8250510163,
        "output": 15231119,
        "cache": 8060607744,
        "reasoning": 5849399,
        "sessions": 214
      },
      "allTime": {
        "tokens": 8265741282,
        "input": 8250510163,
        "output": 15231119,
        "cache": 8060607744,
        "reasoning": 5849399,
        "sessions": 214
      }
    },
    "total": {
      "label": "Total",
      "today": {
        "tokens": 126818196,
        "input": 71307445,
        "output": 260169,
        "cache": 122322176,
        "reasoning": 72160,
        "sessions": 28
      },
      "month": {
        "tokens": 9245532608,
        "input": 8328403132,
        "output": 19530154,
        "cache": 8957427456,
        "reasoning": 6629009,
        "sessions": 990
      },
      "allTime": {
        "tokens": 9245532608,
        "input": 8328403132,
        "output": 19530154,
        "cache": 8957427456,
        "reasoning": 6629009,
        "sessions": 990
      }
    }
  }
}
