{
  "generatedAt": "2026-05-26T17:19:07.249945Z",
  "timezone": "Asia/Tokyo",
  "today": "2026-05-27",
  "month": "2026-05",
  "note": "Hermes uses local sessions table usage. Symphony uses Codex rollout token_count events from Symphony-launched workers. This is not provider billing.",
  "categories": {
    "hermes": {
      "label": "Hermes Agent",
      "today": {
        "tokens": 0,
        "input": 0,
        "output": 0,
        "cache": 0,
        "reasoning": 0,
        "sessions": 0
      },
      "month": {
        "tokens": 1225626241,
        "input": 96648253,
        "output": 5246548,
        "cache": 1122765824,
        "reasoning": 965616,
        "sessions": 960
      },
      "allTime": {
        "tokens": 1225626241,
        "input": 96648253,
        "output": 5246548,
        "cache": 1122765824,
        "reasoning": 965616,
        "sessions": 960
      }
    },
    "symphony": {
      "label": "Symphony",
      "today": {
        "tokens": 0,
        "input": 0,
        "output": 0,
        "cache": 0,
        "reasoning": 0,
        "sessions": 0
      },
      "month": {
        "tokens": 11210578304,
        "input": 11190686696,
        "output": 19891608,
        "cache": 10933680000,
        "reasoning": 7977998,
        "sessions": 250
      },
      "allTime": {
        "tokens": 11210578304,
        "input": 11190686696,
        "output": 19891608,
        "cache": 10933680000,
        "reasoning": 7977998,
        "sessions": 250
      }
    },
    "total": {
      "label": "Total",
      "today": {
        "tokens": 0,
        "input": 0,
        "output": 0,
        "cache": 0,
        "reasoning": 0,
        "sessions": 0
      },
      "month": {
        "tokens": 12436204545,
        "input": 11287334949,
        "output": 25138156,
        "cache": 12056445824,
        "reasoning": 8943614,
        "sessions": 1210
      },
      "allTime": {
        "tokens": 12436204545,
        "input": 11287334949,
        "output": 25138156,
        "cache": 12056445824,
        "reasoning": 8943614,
        "sessions": 1210
      }
    }
  }
}
