{
  "generatedAt": "2026-05-20T20:15:34.072206Z",
  "timezone": "Asia/Tokyo",
  "today": "2026-05-21",
  "month": "2026-05",
  "note": "Hermes uses local sessions table usage. Symphony uses Codex rollout token_count events from Symphony-launched workers. This is not provider billing.",
  "categories": {
    "hermes": {
      "label": "Hermes Agent",
      "today": {
        "tokens": 57793012,
        "input": 3045301,
        "output": 201153,
        "cache": 54510592,
        "reasoning": 35966,
        "sessions": 24
      },
      "month": {
        "tokens": 728978923,
        "input": 63247677,
        "output": 3504580,
        "cache": 661605888,
        "reasoning": 620778,
        "sessions": 663
      },
      "allTime": {
        "tokens": 728978923,
        "input": 63247677,
        "output": 3504580,
        "cache": 661605888,
        "reasoning": 620778,
        "sessions": 663
      }
    },
    "symphony": {
      "label": "Symphony",
      "today": {
        "tokens": 785058282,
        "input": 783592702,
        "output": 1465580,
        "cache": 766473728,
        "reasoning": 502021,
        "sessions": 27
      },
      "month": {
        "tokens": 4082173672,
        "input": 4074107799,
        "output": 8065873,
        "cache": 3970518272,
        "reasoning": 2971409,
        "sessions": 117
      },
      "allTime": {
        "tokens": 4082173672,
        "input": 4074107799,
        "output": 8065873,
        "cache": 3970518272,
        "reasoning": 2971409,
        "sessions": 117
      }
    },
    "total": {
      "label": "Total",
      "today": {
        "tokens": 842851294,
        "input": 786638003,
        "output": 1666733,
        "cache": 820984320,
        "reasoning": 537987,
        "sessions": 51
      },
      "month": {
        "tokens": 4811152595,
        "input": 4137355476,
        "output": 11570453,
        "cache": 4632124160,
        "reasoning": 3592187,
        "sessions": 780
      },
      "allTime": {
        "tokens": 4811152595,
        "input": 4137355476,
        "output": 11570453,
        "cache": 4632124160,
        "reasoning": 3592187,
        "sessions": 780
      }
    }
  }
}
